tg_admin_bot/__main__.py
tg_admin_bot/core/common.py
tg_admin_bot/core/tg.py
tg_admin_bot/funcs/logs.py
tg_admin_bot-24.0.3.dist-info/METADATA
tg_admin_bot-24.0.3.dist-info/WHEEL
tg_admin_bot-24.0.3.dist-info/entry_points.txt
tg_admin_bot-24.0.3.dist-info/top_level.txt
tg_admin_bot-24.0.3.dist-info/RECORD
